colibri/__init__.py
colibri/_native.cpython-312-x86_64-linux-gnu.so
colibri/client.py
colibri/py.typed
colibri/storage.py
colibri/testing.py
colibri/types.py
colibri_stateless-1.1.1.dist-info/METADATA
colibri_stateless-1.1.1.dist-info/WHEEL
colibri_stateless-1.1.1.dist-info/top_level.txt
colibri_stateless-1.1.1.dist-info/RECORD
