Metadata-Version: 2.4
Name: colibri-stateless
Version: 1.1.1
Summary: Python bindings for Colibri stateless Ethereum proof library
Home-page: https://github.com/corpus-core/colibri-stateless
Author: corpus.core
Author-email: "corpus.core" <contact@corpus.core>
Maintainer-email: "corpus.core" <contact@corpus.core>
License: MIT
Project-URL: Homepage, https://github.com/corpus-core/colibri-stateless
Project-URL: Documentation, https://corpus-core.gitbook.io/specification-colibri-stateless/developer-guide/bindings/python
Project-URL: Repository, https://github.com/corpus-core/colibri-stateless
Project-URL: Bug Tracker, https://github.com/corpus-core/colibri-stateless/issues
Keywords: ethereum,blockchain,proof,verification,web3,rpc
Classifier: Development Status :: 4 - Beta
Classifier: Intended Audience :: Developers
Classifier: License :: OSI Approved :: MIT License
Classifier: Operating System :: OS Independent
Classifier: Programming Language :: Python :: 3
Classifier: Programming Language :: Python :: 3.8
Classifier: Programming Language :: Python :: 3.9
Classifier: Programming Language :: Python :: 3.10
Classifier: Programming Language :: Python :: 3.11
Classifier: Programming Language :: Python :: 3.12
Classifier: Topic :: Software Development :: Libraries :: Python Modules
Classifier: Topic :: System :: Networking
Classifier: Topic :: Security :: Cryptography
Requires-Python: >=3.8
Requires-Dist: aiohttp>=3.8.0
Requires-Dist: typing-extensions>=4.0.0
Provides-Extra: dev
Requires-Dist: pytest>=7.0.0; extra == "dev"
Requires-Dist: pytest-asyncio>=0.21.0; extra == "dev"
Requires-Dist: pytest-cov>=4.0.0; extra == "dev"
Requires-Dist: black>=22.0.0; extra == "dev"
Requires-Dist: mypy>=1.0.0; extra == "dev"
Requires-Dist: ruff>=0.1.0; extra == "dev"
Provides-Extra: test
Requires-Dist: pytest>=7.0.0; extra == "test"
Requires-Dist: pytest-asyncio>=0.21.0; extra == "test"
Requires-Dist: pytest-mock>=3.10.0; extra == "test"
Dynamic: author
Dynamic: home-page
Dynamic: requires-python
